cgemail/__init__.py
cgemail/send_email.py
cgemail-1.0.0.dist-info/LICENSE
cgemail-1.0.0.dist-info/METADATA
cgemail-1.0.0.dist-info/WHEEL
cgemail-1.0.0.dist-info/top_level.txt
cgemail-1.0.0.dist-info/RECORD
