Metadata-Version: 2.1
Name: cgemail
Version: 1.0.0
Summary: Lib de envio de e-mail.
Home-page: https://github.com/ramirooliveiracg/cgemail
Author: Gabriel Dalacorte e Rogerio Filho
Author-email: gnunes.servico@gmail.com, crofilho2@gmail.com
License: MIT
Platform: UNKNOWN
Classifier: License :: OSI Approved :: MIT License
Classifier: Programming Language :: Python :: 3
Classifier: Programming Language :: Python :: 3.7
License-File: LICENSE
Requires-Dist: requests
